CHANGES.txt
README.txt
setup.cfg
setup.py
repopencore/__init__.py
repopencore/deliverance.xml
repopencore/deliverance_middleware.py
repopencore/opencore.ini_tmpl
repopencore/opencore_with_tt.ini_tmpl
repopencore/wsgi.py
repopencore.egg-info/PKG-INFO
repopencore.egg-info/SOURCES.txt
repopencore.egg-info/dependency_links.txt
repopencore.egg-info/entry_points.txt
repopencore.egg-info/not-zip-safe
repopencore.egg-info/requires.txt
repopencore.egg-info/top_level.txt