Metadata-Version: 1.0
Name: repopencore
Version: 0.3
Summary: run opencore with repoze.zope2
Home-page: UNKNOWN
Author: Ethan Jucovy
Author-email: ejucovy@gmail.com
License: GPL
Platform: UNKNOWN
